__init__.py
omicsone_volcano/__init__.py
omicsone_volcano/main.py
omicsone_volcano/plugins/param.cp39-win_amd64.pyd
omicsone_volcano/plugins/volcano.cp39-win_amd64.pyd
omicsone_volcano-0.1.0.dist-info/LICENSE
omicsone_volcano-0.1.0.dist-info/METADATA
omicsone_volcano-0.1.0.dist-info/WHEEL
omicsone_volcano-0.1.0.dist-info/entry_points.txt
omicsone_volcano-0.1.0.dist-info/top_level.txt
omicsone_volcano-0.1.0.dist-info/RECORD
